<markdown_skeleton_root>
  <block_element>
    <ArrayOfMarkdownBlockBase xmlns:xsd="http://www.w3.org/2001/XMLSchema" xmlns:xsi="http://www.w3.org/2001/XMLSchema-instance">
      <MarkdownBlockBase
        xsi:type="MarkdownHeaderBlock"
        item_id="45a93b1e-f4f5-499d-80f8-daccb2e52f42"
        item_type="Header"
        item_footer="footer_not_set"
        trans_unit_id="45a93b1e-f4f5-499d-80f8-daccb2e52f42">
        <segment
          trans_unit_id="101">
          <SegmentId>3d7e4da5-65b8-4434-b042-20ca88f3cc1c</SegmentId>
          <InternalNormalItem
            internal_item_id="1"
            internal_item_parent_id="101"
            trans_unit_id="101-1"
            internal_item_type="Normal">
            <internal_items />
          </InternalNormalItem>
        </segment>
        <header_type>Star</header_type>
        <header_level>1</header_level>
      </MarkdownBlockBase>
      <MarkdownBlockBase
        xsi:type="MarkdownBlockQuote"
        item_id="4382715f-351c-4502-83e7-a0c36972d1fe"
        item_type="BlockQuote"
        item_footer=""
        trans_unit_id="4382715f-351c-4502-83e7-a0c36972d1fe">
        <MarkdownParagraphBlock
          item_id="47b036d9-94b7-4c6c-b7a7-2686ceaea565"
          item_type="NormalParagraph"
          item_footer="footer_not_set"
          trans_unit_id="47b036d9-94b7-4c6c-b7a7-2686ceaea565">
          <Lines>
            <MarkdownLine>
              <LineId>04f78888-09f2-4df2-aa5e-b65c8c1e2c35</LineId>
              <paragraph_segments>
                <MarkdownSegment
                  trans_unit_id="102">
                  <SegmentId>4698eddd-29ba-4ee3-beca-d9ba49df46b4</SegmentId>
                  <InternalNormalItem
                    internal_item_id="1"
                    internal_item_parent_id="102"
                    trans_unit_id="102-1"
                    internal_item_type="Normal">
                    <internal_items />
                  </InternalNormalItem>
                </MarkdownSegment>
              </paragraph_segments>
              <PrefixWSLength>1</PrefixWSLength>
              <SuffixWSLength>0</SuffixWSLength>
            </MarkdownLine>
          </Lines>
          <paragraph_segments>
            <MarkdownSegment
              trans_unit_id="102">
              <SegmentId>4698eddd-29ba-4ee3-beca-d9ba49df46b4</SegmentId>
              <InternalNormalItem
                internal_item_id="1"
                internal_item_parent_id="102"
                trans_unit_id="102-1"
                internal_item_type="Normal">
                <internal_items />
              </InternalNormalItem>
            </MarkdownSegment>
          </paragraph_segments>
        </MarkdownParagraphBlock>
      </MarkdownBlockBase>
      <MarkdownBlockBase
        xsi:type="MarkdownParagraphBlock"
        item_id="cc59b4ca-378f-4705-9121-772fa889f2fa"
        item_type="NormalParagraph"
        item_footer=""
        trans_unit_id="cc59b4ca-378f-4705-9121-772fa889f2fa">
        <Lines>
          <MarkdownLine>
            <LineId>d61ee93f-8244-4652-9187-5890175114a7</LineId>
            <paragraph_segments>
              <MarkdownSegment
                trans_unit_id="103">
                <SegmentId>dc559022-183b-4fd1-8e73-d77b5aaa09b5</SegmentId>
                <InternalNormalItem
                  internal_item_id="1"
                  internal_item_parent_id="103"
                  trans_unit_id="103-1"
                  internal_item_type="Normal">
                  <internal_items />
                </InternalNormalItem>
              </MarkdownSegment>
            </paragraph_segments>
            <PrefixWSLength>0</PrefixWSLength>
            <SuffixWSLength>0</SuffixWSLength>
          </MarkdownLine>
        </Lines>
        <paragraph_segments>
          <MarkdownSegment
            trans_unit_id="103">
            <SegmentId>dc559022-183b-4fd1-8e73-d77b5aaa09b5</SegmentId>
            <InternalNormalItem
              internal_item_id="1"
              internal_item_parent_id="103"
              trans_unit_id="103-1"
              internal_item_type="Normal">
              <internal_items />
            </InternalNormalItem>
          </MarkdownSegment>
        </paragraph_segments>
      </MarkdownBlockBase>
      <MarkdownBlockBase
        xsi:type="MarkdownHeaderBlock"
        item_id="f93b8b47-fd26-4f51-87d7-0168db6cf48e"
        item_type="Header"
        item_footer="footer_not_set"
        trans_unit_id="f93b8b47-fd26-4f51-87d7-0168db6cf48e">
        <segment
          trans_unit_id="104">
          <SegmentId>dfb31a7d-3215-4b1f-89f6-4be5cb59d312</SegmentId>
          <InternalNormalItem
            internal_item_id="1"
            internal_item_parent_id="104"
            trans_unit_id="104-1"
            internal_item_type="Normal">
            <internal_items />
          </InternalNormalItem>
        </segment>
        <header_type>Star</header_type>
        <header_level>2</header_level>
      </MarkdownBlockBase>
      <MarkdownBlockBase
        xsi:type="MarkdownParagraphBlock"
        item_id="69b3366d-2693-431e-853a-8f322e471ae5"
        item_type="NormalParagraph"
        item_footer="&#xA;"
        trans_unit_id="69b3366d-2693-431e-853a-8f322e471ae5">
        <Lines>
          <MarkdownLine>
            <LineId>d772b887-c68e-46c7-8328-d5f5e4226f6e</LineId>
            <paragraph_segments>
              <MarkdownSegment
                trans_unit_id="105">
                <SegmentId>5c0df02b-599e-4407-a797-59af55539c0b</SegmentId>
                <InternalNormalItem
                  internal_item_id="1"
                  internal_item_parent_id="105"
                  trans_unit_id="105-1"
                  internal_item_type="Normal">
                  <internal_items />
                </InternalNormalItem>
                <LinkItem
                  internal_item_id="2"
                  internal_item_parent_id="105"
                  trans_unit_id="105-2"
                  internal_item_type="Link">
                  <internal_items />
                  <internal_link_type>Inline</internal_link_type>
                  <internal_link_text>Enable-DscDebug</internal_link_text>
                  <internal_link_url>https://technet.microsoft.com/en-us/library/mt517870.aspx</internal_link_url>
                  <internal_link_title />
                </LinkItem>
                <InternalNormalItem
                  internal_item_id="3"
                  internal_item_parent_id="105"
                  trans_unit_id="105-3"
                  internal_item_type="Normal">
                  <internal_items />
                </InternalNormalItem>
              </MarkdownSegment>
              <MarkdownSegment
                trans_unit_id="106">
                <SegmentId>0b496f44-a5a0-44ce-8da2-dee0f400c937</SegmentId>
                <InternalNormalItem
                  internal_item_id="1"
                  internal_item_parent_id="106"
                  trans_unit_id="106-1"
                  internal_item_type="Normal">
                  <internal_items />
                </InternalNormalItem>
                <MarkdownInternalBoldItem
                  internal_item_id="2"
                  internal_item_parent_id="106"
                  trans_unit_id="106-2"
                  internal_item_type="Bold">
                  <internal_items />
                  <internal_itatic_bold_item_type>Star</internal_itatic_bold_item_type>
                </MarkdownInternalBoldItem>
                <InternalNormalItem
                  internal_item_id="3"
                  internal_item_parent_id="106"
                  trans_unit_id="106-3"
                  internal_item_type="Normal">
                  <internal_items />
                </InternalNormalItem>
              </MarkdownSegment>
              <MarkdownSegment
                trans_unit_id="107">
                <SegmentId>4464a946-ba1c-4784-afc8-67a9c6731a81</SegmentId>
                <InternalNormalItem
                  internal_item_id="1"
                  internal_item_parent_id="107"
                  trans_unit_id="107-1"
                  internal_item_type="Normal">
                  <internal_items />
                </InternalNormalItem>
                <LinkItem
                  internal_item_id="2"
                  internal_item_parent_id="107"
                  trans_unit_id="107-2"
                  internal_item_type="Link">
                  <internal_items />
                  <internal_link_type>Inline</internal_link_type>
                  <internal_link_text>Get-DscLocalConfigurationManager</internal_link_text>
                  <internal_link_url>https://technet.microsoft.com/en-us/library/dn407378.aspx</internal_link_url>
                  <internal_link_title />
                </LinkItem>
                <InternalNormalItem
                  internal_item_id="3"
                  internal_item_parent_id="107"
                  trans_unit_id="107-3"
                  internal_item_type="Normal">
                  <internal_items />
                </InternalNormalItem>
              </MarkdownSegment>
              <MarkdownSegment
                trans_unit_id="108">
                <SegmentId>eed9dbfd-f92a-483d-b855-c495c4eaa699</SegmentId>
                <InternalNormalItem
                  internal_item_id="1"
                  internal_item_parent_id="108"
                  trans_unit_id="108-1"
                  internal_item_type="Normal">
                  <internal_items />
                </InternalNormalItem>
              </MarkdownSegment>
            </paragraph_segments>
            <PrefixWSLength>0</PrefixWSLength>
            <SuffixWSLength>0</SuffixWSLength>
          </MarkdownLine>
        </Lines>
        <paragraph_segments>
          <MarkdownSegment
            trans_unit_id="105">
            <SegmentId>5c0df02b-599e-4407-a797-59af55539c0b</SegmentId>
            <InternalNormalItem
              internal_item_id="1"
              internal_item_parent_id="105"
              trans_unit_id="105-1"
              internal_item_type="Normal">
              <internal_items />
            </InternalNormalItem>
            <LinkItem
              internal_item_id="2"
              internal_item_parent_id="105"
              trans_unit_id="105-2"
              internal_item_type="Link">
              <internal_items />
              <internal_link_type>Inline</internal_link_type>
              <internal_link_text>Enable-DscDebug</internal_link_text>
              <internal_link_url>https://technet.microsoft.com/en-us/library/mt517870.aspx</internal_link_url>
              <internal_link_title />
            </LinkItem>
            <InternalNormalItem
              internal_item_id="3"
              internal_item_parent_id="105"
              trans_unit_id="105-3"
              internal_item_type="Normal">
              <internal_items />
            </InternalNormalItem>
          </MarkdownSegment>
          <MarkdownSegment
            trans_unit_id="106">
            <SegmentId>0b496f44-a5a0-44ce-8da2-dee0f400c937</SegmentId>
            <InternalNormalItem
              internal_item_id="1"
              internal_item_parent_id="106"
              trans_unit_id="106-1"
              internal_item_type="Normal">
              <internal_items />
            </InternalNormalItem>
            <MarkdownInternalBoldItem
              internal_item_id="2"
              internal_item_parent_id="106"
              trans_unit_id="106-2"
              internal_item_type="Bold">
              <internal_items />
              <internal_itatic_bold_item_type>Star</internal_itatic_bold_item_type>
            </MarkdownInternalBoldItem>
            <InternalNormalItem
              internal_item_id="3"
              internal_item_parent_id="106"
              trans_unit_id="106-3"
              internal_item_type="Normal">
              <internal_items />
            </InternalNormalItem>
          </MarkdownSegment>
          <MarkdownSegment
            trans_unit_id="107">
            <SegmentId>4464a946-ba1c-4784-afc8-67a9c6731a81</SegmentId>
            <InternalNormalItem
              internal_item_id="1"
              internal_item_parent_id="107"
              trans_unit_id="107-1"
              internal_item_type="Normal">
              <internal_items />
            </InternalNormalItem>
            <LinkItem
              internal_item_id="2"
              internal_item_parent_id="107"
              trans_unit_id="107-2"
              internal_item_type="Link">
              <internal_items />
              <internal_link_type>Inline</internal_link_type>
              <internal_link_text>Get-DscLocalConfigurationManager</internal_link_text>
              <internal_link_url>https://technet.microsoft.com/en-us/library/dn407378.aspx</internal_link_url>
              <internal_link_title />
            </LinkItem>
            <InternalNormalItem
              internal_item_id="3"
              internal_item_parent_id="107"
              trans_unit_id="107-3"
              internal_item_type="Normal">
              <internal_items />
            </InternalNormalItem>
          </MarkdownSegment>
          <MarkdownSegment
            trans_unit_id="108">
            <SegmentId>eed9dbfd-f92a-483d-b855-c495c4eaa699</SegmentId>
            <InternalNormalItem
              internal_item_id="1"
              internal_item_parent_id="108"
              trans_unit_id="108-1"
              internal_item_type="Normal">
              <internal_items />
            </InternalNormalItem>
          </MarkdownSegment>
        </paragraph_segments>
      </MarkdownBlockBase>
      <MarkdownBlockBase
        xsi:type="MarkdownFencedCodeBlock"
        item_id="9f83278c-1c4d-44b2-a0b1-4534603ed3bd"
        item_type="FencedCodeBlock"
        item_footer="&#xA;"
        trans_unit_id="9f83278c-1c4d-44b2-a0b1-4534603ed3bd">
        <codeblock_wraper>```</codeblock_wraper>
        <code_block>PS C:\DebugTest&gt; $LCM = Get-DscLocalConfigurationManager

PS C:\DebugTest&gt; $LCM.DebugMode
NONE

PS C:\DebugTest&gt; Enable-DscDebug -BreakAll

PS C:\DebugTest&gt; $LCM = Get-DscLocalConfigurationManager

PS C:\DebugTest&gt; $LCM.DebugMode
ForceModuleImport
ResourceScriptBreakAll

PS C:\DebugTest&gt;</code_block>
        <fenced_code_lang>powershell</fenced_code_lang>
      </MarkdownBlockBase>
      <MarkdownBlockBase
        xsi:type="MarkdownHeaderBlock"
        item_id="d49ab4a4-b640-4c08-a6b4-d832132ee677"
        item_type="Header"
        item_footer="footer_not_set"
        trans_unit_id="d49ab4a4-b640-4c08-a6b4-d832132ee677">
        <segment
          trans_unit_id="109">
          <SegmentId>b3c2c774-c813-44e5-88b4-eb99317f1d11</SegmentId>
          <InternalNormalItem
            internal_item_id="1"
            internal_item_parent_id="109"
            trans_unit_id="109-1"
            internal_item_type="Normal">
            <internal_items />
          </InternalNormalItem>
        </segment>
        <header_type>Star</header_type>
        <header_level>2</header_level>
      </MarkdownBlockBase>
      <MarkdownBlockBase
        xsi:type="MarkdownParagraphBlock"
        item_id="892b0f91-4c99-4827-a20f-a3abaf689372"
        item_type="NormalParagraph"
        item_footer=""
        trans_unit_id="892b0f91-4c99-4827-a20f-a3abaf689372">
        <Lines>
          <MarkdownLine>
            <LineId>e9ca8126-e9ca-436f-a9a2-8b7f6f2305f5</LineId>
            <paragraph_segments>
              <MarkdownSegment
                trans_unit_id="110">
                <SegmentId>723941e6-ba04-4981-aaa5-a4a509728c86</SegmentId>
                <InternalNormalItem
                  internal_item_id="1"
                  internal_item_parent_id="110"
                  trans_unit_id="110-1"
                  internal_item_type="Normal">
                  <internal_items />
                </InternalNormalItem>
              </MarkdownSegment>
              <MarkdownSegment
                trans_unit_id="111">
                <SegmentId>06a695d8-7bd9-4e29-95e1-43301e289f6f</SegmentId>
                <InternalNormalItem
                  internal_item_id="1"
                  internal_item_parent_id="111"
                  trans_unit_id="111-1"
                  internal_item_type="Normal">
                  <internal_items />
                </InternalNormalItem>
                <LinkItem
                  internal_item_id="2"
                  internal_item_parent_id="111"
                  trans_unit_id="111-2"
                  internal_item_type="Link">
                  <internal_items />
                  <internal_link_type>Inline</internal_link_type>
                  <internal_link_text>WindowsFeature</internal_link_text>
                  <internal_link_url>windowsfeatureResource.md</internal_link_url>
                  <internal_link_title />
                </LinkItem>
                <InternalNormalItem
                  internal_item_id="3"
                  internal_item_parent_id="111"
                  trans_unit_id="111-3"
                  internal_item_type="Normal">
                  <internal_items />
                </InternalNormalItem>
              </MarkdownSegment>
            </paragraph_segments>
            <PrefixWSLength>0</PrefixWSLength>
            <SuffixWSLength>0</SuffixWSLength>
          </MarkdownLine>
        </Lines>
        <paragraph_segments>
          <MarkdownSegment
            trans_unit_id="110">
            <SegmentId>723941e6-ba04-4981-aaa5-a4a509728c86</SegmentId>
            <InternalNormalItem
              internal_item_id="1"
              internal_item_parent_id="110"
              trans_unit_id="110-1"
              internal_item_type="Normal">
              <internal_items />
            </InternalNormalItem>
          </MarkdownSegment>
          <MarkdownSegment
            trans_unit_id="111">
            <SegmentId>06a695d8-7bd9-4e29-95e1-43301e289f6f</SegmentId>
            <InternalNormalItem
              internal_item_id="1"
              internal_item_parent_id="111"
              trans_unit_id="111-1"
              internal_item_type="Normal">
              <internal_items />
            </InternalNormalItem>
            <LinkItem
              internal_item_id="2"
              internal_item_parent_id="111"
              trans_unit_id="111-2"
              internal_item_type="Link">
              <internal_items />
              <internal_link_type>Inline</internal_link_type>
              <internal_link_text>WindowsFeature</internal_link_text>
              <internal_link_url>windowsfeatureResource.md</internal_link_url>
              <internal_link_title />
            </LinkItem>
            <InternalNormalItem
              internal_item_id="3"
              internal_item_parent_id="111"
              trans_unit_id="111-3"
              internal_item_type="Normal">
              <internal_items />
            </InternalNormalItem>
          </MarkdownSegment>
        </paragraph_segments>
      </MarkdownBlockBase>
      <MarkdownBlockBase
        xsi:type="MarkdownFencedCodeBlock"
        item_id="682f20c3-c063-420c-865d-2c31755541ce"
        item_type="FencedCodeBlock"
        item_footer="footer_not_set"
        trans_unit_id="682f20c3-c063-420c-865d-2c31755541ce">
        <codeblock_wraper>```</codeblock_wraper>
        <code_block>Configuration PSWebAccess
    {
    Import-DscResource -ModuleName 'PsDesiredStateConfiguration'
    Node localhost
        {
        WindowsFeature PSWA
            {
            Name = 'WindowsPowerShellWebAccess'
            Ensure = 'Present'
            }
        }
    }
PSWebAccess</code_block>
        <fenced_code_lang>powershell</fenced_code_lang>
      </MarkdownBlockBase>
      <MarkdownBlockBase
        xsi:type="MarkdownParagraphBlock"
        item_id="d0022e40-254d-4694-8b18-14f508fa6cd0"
        item_type="NormalParagraph"
        item_footer=""
        trans_unit_id="d0022e40-254d-4694-8b18-14f508fa6cd0">
        <Lines>
          <MarkdownLine>
            <LineId>e7cbaf8e-e597-4143-a09f-1459d81fde06</LineId>
            <paragraph_segments>
              <MarkdownSegment
                trans_unit_id="112">
                <SegmentId>579ee740-ebff-4272-84d2-ee7489ea3120</SegmentId>
                <InternalNormalItem
                  internal_item_id="1"
                  internal_item_parent_id="112"
                  trans_unit_id="112-1"
                  internal_item_type="Normal">
                  <internal_items />
                </InternalNormalItem>
                <LinkItem
                  internal_item_id="2"
                  internal_item_parent_id="112"
                  trans_unit_id="112-2"
                  internal_item_type="Link">
                  <internal_items />
                  <internal_link_type>Inline</internal_link_type>
                  <internal_link_text>Start-DscConfiguration</internal_link_text>
                  <internal_link_url>https://technet.microsoft.com/en-us/library/dn521623.aspx</internal_link_url>
                  <internal_link_title />
                </LinkItem>
                <InternalNormalItem
                  internal_item_id="3"
                  internal_item_parent_id="112"
                  trans_unit_id="112-3"
                  internal_item_type="Normal">
                  <internal_items />
                </InternalNormalItem>
              </MarkdownSegment>
              <MarkdownSegment
                trans_unit_id="113">
                <SegmentId>7b58263c-b4c9-4ce0-a482-4bf24e01d13c</SegmentId>
                <InternalNormalItem
                  internal_item_id="1"
                  internal_item_parent_id="113"
                  trans_unit_id="113-1"
                  internal_item_type="Normal">
                  <internal_items />
                </InternalNormalItem>
              </MarkdownSegment>
            </paragraph_segments>
            <PrefixWSLength>0</PrefixWSLength>
            <SuffixWSLength>0</SuffixWSLength>
          </MarkdownLine>
          <MarkdownLine>
            <LineId>8480ec11-8b84-402f-a64a-2013eed874d5</LineId>
            <paragraph_segments>
              <MarkdownSegment
                trans_unit_id="114">
                <SegmentId>aa33be7d-1d0d-405d-9cb0-793e2765002f</SegmentId>
                <InternalNormalItem
                  internal_item_id="1"
                  internal_item_parent_id="114"
                  trans_unit_id="114-1"
                  internal_item_type="Normal">
                  <internal_items />
                </InternalNormalItem>
              </MarkdownSegment>
              <MarkdownSegment
                trans_unit_id="115">
                <SegmentId>357ce7c6-2339-474a-8089-3c22b488f0ec</SegmentId>
                <InternalNormalItem
                  internal_item_id="1"
                  internal_item_parent_id="115"
                  trans_unit_id="115-1"
                  internal_item_type="Normal">
                  <internal_items />
                </InternalNormalItem>
                <CodeSpanItem
                  internal_item_id="2"
                  internal_item_parent_id="115"
                  trans_unit_id="115-2"
                  internal_item_type="CodeSpan">
                  <internal_items />
                  <ItemValue>-Verbose</ItemValue>
                </CodeSpanItem>
                <InternalNormalItem
                  internal_item_id="3"
                  internal_item_parent_id="115"
                  trans_unit_id="115-3"
                  internal_item_type="Normal">
                  <internal_items />
                </InternalNormalItem>
                <CodeSpanItem
                  internal_item_id="4"
                  internal_item_parent_id="115"
                  trans_unit_id="115-4"
                  internal_item_type="CodeSpan">
                  <internal_items />
                  <ItemValue>-Wait</ItemValue>
                </CodeSpanItem>
                <InternalNormalItem
                  internal_item_id="5"
                  internal_item_parent_id="115"
                  trans_unit_id="115-5"
                  internal_item_type="Normal">
                  <internal_items />
                </InternalNormalItem>
              </MarkdownSegment>
            </paragraph_segments>
            <PrefixWSLength>0</PrefixWSLength>
            <SuffixWSLength>0</SuffixWSLength>
          </MarkdownLine>
          <MarkdownLine>
            <LineId>8c267473-00d9-4009-b454-604bac3a19c4</LineId>
            <paragraph_segments>
              <MarkdownSegment
                trans_unit_id="116">
                <SegmentId>f6616e29-3ab2-4726-93f3-f25a2e000d7c</SegmentId>
                <InternalNormalItem
                  internal_item_id="1"
                  internal_item_parent_id="116"
                  trans_unit_id="116-1"
                  internal_item_type="Normal">
                  <internal_items />
                </InternalNormalItem>
              </MarkdownSegment>
            </paragraph_segments>
            <PrefixWSLength>0</PrefixWSLength>
            <SuffixWSLength>0</SuffixWSLength>
          </MarkdownLine>
        </Lines>
        <paragraph_segments>
          <MarkdownSegment
            trans_unit_id="112">
            <SegmentId>579ee740-ebff-4272-84d2-ee7489ea3120</SegmentId>
            <InternalNormalItem
              internal_item_id="1"
              internal_item_parent_id="112"
              trans_unit_id="112-1"
              internal_item_type="Normal">
              <internal_items />
            </InternalNormalItem>
            <LinkItem
              internal_item_id="2"
              internal_item_parent_id="112"
              trans_unit_id="112-2"
              internal_item_type="Link">
              <internal_items />
              <internal_link_type>Inline</internal_link_type>
              <internal_link_text>Start-DscConfiguration</internal_link_text>
              <internal_link_url>https://technet.microsoft.com/en-us/library/dn521623.aspx</internal_link_url>
              <internal_link_title />
            </LinkItem>
            <InternalNormalItem
              internal_item_id="3"
              internal_item_parent_id="112"
              trans_unit_id="112-3"
              internal_item_type="Normal">
              <internal_items />
            </InternalNormalItem>
          </MarkdownSegment>
          <MarkdownSegment
            trans_unit_id="113">
            <SegmentId>7b58263c-b4c9-4ce0-a482-4bf24e01d13c</SegmentId>
            <InternalNormalItem
              internal_item_id="1"
              internal_item_parent_id="113"
              trans_unit_id="113-1"
              internal_item_type="Normal">
              <internal_items />
            </InternalNormalItem>
          </MarkdownSegment>
          <MarkdownSegment
            trans_unit_id="114">
            <SegmentId>aa33be7d-1d0d-405d-9cb0-793e2765002f</SegmentId>
            <InternalNormalItem
              internal_item_id="1"
              internal_item_parent_id="114"
              trans_unit_id="114-1"
              internal_item_type="Normal">
              <internal_items />
            </InternalNormalItem>
          </MarkdownSegment>
          <MarkdownSegment
            trans_unit_id="115">
            <SegmentId>357ce7c6-2339-474a-8089-3c22b488f0ec</SegmentId>
            <InternalNormalItem
              internal_item_id="1"
              internal_item_parent_id="115"
              trans_unit_id="115-1"
              internal_item_type="Normal">
              <internal_items />
            </InternalNormalItem>
            <CodeSpanItem
              internal_item_id="2"
              internal_item_parent_id="115"
              trans_unit_id="115-2"
              internal_item_type="CodeSpan">
              <internal_items />
              <ItemValue>-Verbose</ItemValue>
            </CodeSpanItem>
            <InternalNormalItem
              internal_item_id="3"
              internal_item_parent_id="115"
              trans_unit_id="115-3"
              internal_item_type="Normal">
              <internal_items />
            </InternalNormalItem>
            <CodeSpanItem
              internal_item_id="4"
              internal_item_parent_id="115"
              trans_unit_id="115-4"
              internal_item_type="CodeSpan">
              <internal_items />
              <ItemValue>-Wait</ItemValue>
            </CodeSpanItem>
            <InternalNormalItem
              internal_item_id="5"
              internal_item_parent_id="115"
              trans_unit_id="115-5"
              internal_item_type="Normal">
              <internal_items />
            </InternalNormalItem>
          </MarkdownSegment>
          <MarkdownSegment
            trans_unit_id="116">
            <SegmentId>f6616e29-3ab2-4726-93f3-f25a2e000d7c</SegmentId>
            <InternalNormalItem
              internal_item_id="1"
              internal_item_parent_id="116"
              trans_unit_id="116-1"
              internal_item_type="Normal">
              <internal_items />
            </InternalNormalItem>
          </MarkdownSegment>
        </paragraph_segments>
      </MarkdownBlockBase>
      <MarkdownBlockBase
        xsi:type="MarkdownFencedCodeBlock"
        item_id="06900eec-961b-4047-826c-25480c79537b"
        item_type="FencedCodeBlock"
        item_footer="footer_not_set"
        trans_unit_id="06900eec-961b-4047-826c-25480c79537b">
        <codeblock_wraper>```</codeblock_wraper>
        <code_block>PS C:\DebugTest&gt; Start-DscConfiguration .\PSWebAccess -Wait -Verbose
VERBOSE: Perform operation 'Invoke CimMethod' with following parameters, ''methodName' = SendConfigurationApply,'className' = MSFT_DSCLocalConfiguration
Manager,'namespaceName' = root/Microsoft/Windows/DesiredStateConfiguration'.
VERBOSE: An LCM method call arrived from computer TEST-SRV with user sid S-1-5-21-2127521184-1604012920-1887927527-108583.
VERBOSE: An LCM method call arrived from computer TEST-SRV with user sid S-1-5-21-2127521184-1604012920-1887927527-108583.
VERBOSE: [TEST-SRV]: LCM:  [ Start  Set      ]
WARNING: [TEST-SRV]:                            [DSCEngine] Warning LCM is in Debug 'ResourceScriptBreakAll' mode.  Resource script processing will 
be stopped to wait for PowerShell script debugger to attach.
VERBOSE: [TEST-SRV]:                            [DSCEngine] Importing the module C:\WINDOWS\system32\WindowsPowerShell\v1.0\Modules\PSDesiredStateCo
nfiguration\DscResources\MSFT_RoleResource\MSFT_RoleResource.psm1 in force mode.
VERBOSE: [TEST-SRV]: LCM:  [ Start  Resource ]  [[WindowsFeature]PSWA]
VERBOSE: [TEST-SRV]: LCM:  [ Start  Test     ]  [[WindowsFeature]PSWA]
VERBOSE: [TEST-SRV]:                            [[WindowsFeature]PSWA] Importing the module MSFT_RoleResource in force mode.
WARNING: [TEST-SRV]:                            [[WindowsFeature]PSWA] Resource is waiting for PowerShell script debugger to attach.  Use the follow
ing commands to begin debugging this resource script:
Enter-PSSession -ComputerName TEST-SRV -Credential &lt;credentials&gt;
Enter-PSHostProcess -Id 9000 -AppDomainName DscPsPluginWkr_AppDomain
Debug-Runspace -Id 9</code_block>
        <fenced_code_lang>powershell</fenced_code_lang>
      </MarkdownBlockBase>
      <MarkdownBlockBase
        xsi:type="MarkdownParagraphBlock"
        item_id="0d49b374-4ed0-470a-9801-6f424c153549"
        item_type="NormalParagraph"
        item_footer=""
        trans_unit_id="0d49b374-4ed0-470a-9801-6f424c153549">
        <Lines>
          <MarkdownLine>
            <LineId>c029308a-a946-40c9-b45d-ac44d21269a4</LineId>
            <paragraph_segments>
              <MarkdownSegment
                trans_unit_id="117">
                <SegmentId>de2e9c50-e835-4705-a505-de8d0851ac9d</SegmentId>
                <InternalNormalItem
                  internal_item_id="1"
                  internal_item_parent_id="117"
                  trans_unit_id="117-1"
                  internal_item_type="Normal">
                  <internal_items />
                </InternalNormalItem>
              </MarkdownSegment>
              <MarkdownSegment
                trans_unit_id="118">
                <SegmentId>ecb1c953-e237-49d5-b905-92696ad75bd1</SegmentId>
                <InternalNormalItem
                  internal_item_id="1"
                  internal_item_parent_id="118"
                  trans_unit_id="118-1"
                  internal_item_type="Normal">
                  <internal_items />
                </InternalNormalItem>
              </MarkdownSegment>
            </paragraph_segments>
            <PrefixWSLength>0</PrefixWSLength>
            <SuffixWSLength>0</SuffixWSLength>
          </MarkdownLine>
        </Lines>
        <paragraph_segments>
          <MarkdownSegment
            trans_unit_id="117">
            <SegmentId>de2e9c50-e835-4705-a505-de8d0851ac9d</SegmentId>
            <InternalNormalItem
              internal_item_id="1"
              internal_item_parent_id="117"
              trans_unit_id="117-1"
              internal_item_type="Normal">
              <internal_items />
            </InternalNormalItem>
          </MarkdownSegment>
          <MarkdownSegment
            trans_unit_id="118">
            <SegmentId>ecb1c953-e237-49d5-b905-92696ad75bd1</SegmentId>
            <InternalNormalItem
              internal_item_id="1"
              internal_item_parent_id="118"
              trans_unit_id="118-1"
              internal_item_type="Normal">
              <internal_items />
            </InternalNormalItem>
          </MarkdownSegment>
        </paragraph_segments>
      </MarkdownBlockBase>
      <MarkdownBlockBase
        xsi:type="MarkdownHeaderBlock"
        item_id="ccd5880c-562b-40be-843d-afa1553feb54"
        item_type="Header"
        item_footer="footer_not_set"
        trans_unit_id="ccd5880c-562b-40be-843d-afa1553feb54">
        <segment
          trans_unit_id="119">
          <SegmentId>c9b981a1-b2bd-4491-8767-bde3e2f320d7</SegmentId>
          <InternalNormalItem
            internal_item_id="1"
            internal_item_parent_id="119"
            trans_unit_id="119-1"
            internal_item_type="Normal">
            <internal_items />
          </InternalNormalItem>
        </segment>
        <header_type>Star</header_type>
        <header_level>2</header_level>
      </MarkdownBlockBase>
      <MarkdownBlockBase
        xsi:type="MarkdownParagraphBlock"
        item_id="4a146539-397e-4dfb-9b33-5daf8f146c5e"
        item_type="NormalParagraph"
        item_footer="&#xA;&#xA;&#xA;&#xA;&#xA;"
        trans_unit_id="4a146539-397e-4dfb-9b33-5daf8f146c5e">
        <Lines>
          <MarkdownLine>
            <LineId>69e6c554-9c08-4853-9a7e-457b62c947ec</LineId>
            <paragraph_segments>
              <MarkdownSegment
                trans_unit_id="120">
                <SegmentId>832c3fc5-3227-4c21-a129-769408dda029</SegmentId>
                <InternalNormalItem
                  internal_item_id="1"
                  internal_item_parent_id="120"
                  trans_unit_id="120-1"
                  internal_item_type="Normal">
                  <internal_items />
                </InternalNormalItem>
                <CodeSpanItem
                  internal_item_id="2"
                  internal_item_parent_id="120"
                  trans_unit_id="120-2"
                  internal_item_type="CodeSpan">
                  <internal_items />
                  <ItemValue>Start-DscConifiguration</ItemValue>
                </CodeSpanItem>
                <InternalNormalItem
                  internal_item_id="3"
                  internal_item_parent_id="120"
                  trans_unit_id="120-3"
                  internal_item_type="Normal">
                  <internal_items />
                </InternalNormalItem>
                <CodeSpanItem
                  internal_item_id="4"
                  internal_item_parent_id="120"
                  trans_unit_id="120-4"
                  internal_item_type="CodeSpan">
                  <internal_items />
                  <ItemValue>&lt;credentials&gt;</ItemValue>
                </CodeSpanItem>
                <InternalNormalItem
                  internal_item_id="5"
                  internal_item_parent_id="120"
                  trans_unit_id="120-5"
                  internal_item_type="Normal">
                  <internal_items />
                </InternalNormalItem>
              </MarkdownSegment>
            </paragraph_segments>
            <PrefixWSLength>0</PrefixWSLength>
            <SuffixWSLength>0</SuffixWSLength>
          </MarkdownLine>
          <MarkdownLine>
            <LineId>e197d7d9-01be-4b49-b1a4-e5ddab5f8cd6</LineId>
            <paragraph_segments>
              <MarkdownSegment
                trans_unit_id="121">
                <SegmentId>3c0ea4ce-f1be-42f5-bcee-29c4403d4f70</SegmentId>
                <InternalNormalItem
                  internal_item_id="1"
                  internal_item_parent_id="121"
                  trans_unit_id="121-1"
                  internal_item_type="Normal">
                  <internal_items />
                </InternalNormalItem>
              </MarkdownSegment>
              <MarkdownSegment
                trans_unit_id="122">
                <SegmentId>f11b8e3c-1792-484b-8362-85b218b707f6</SegmentId>
                <InternalNormalItem
                  internal_item_id="1"
                  internal_item_parent_id="122"
                  trans_unit_id="122-1"
                  internal_item_type="Normal">
                  <internal_items />
                </InternalNormalItem>
              </MarkdownSegment>
            </paragraph_segments>
            <PrefixWSLength>0</PrefixWSLength>
            <SuffixWSLength>0</SuffixWSLength>
          </MarkdownLine>
        </Lines>
        <paragraph_segments>
          <MarkdownSegment
            trans_unit_id="120">
            <SegmentId>832c3fc5-3227-4c21-a129-769408dda029</SegmentId>
            <InternalNormalItem
              internal_item_id="1"
              internal_item_parent_id="120"
              trans_unit_id="120-1"
              internal_item_type="Normal">
              <internal_items />
            </InternalNormalItem>
            <CodeSpanItem
              internal_item_id="2"
              internal_item_parent_id="120"
              trans_unit_id="120-2"
              internal_item_type="CodeSpan">
              <internal_items />
              <ItemValue>Start-DscConifiguration</ItemValue>
            </CodeSpanItem>
            <InternalNormalItem
              internal_item_id="3"
              internal_item_parent_id="120"
              trans_unit_id="120-3"
              internal_item_type="Normal">
              <internal_items />
            </InternalNormalItem>
            <CodeSpanItem
              internal_item_id="4"
              internal_item_parent_id="120"
              trans_unit_id="120-4"
              internal_item_type="CodeSpan">
              <internal_items />
              <ItemValue>&lt;credentials&gt;</ItemValue>
            </CodeSpanItem>
            <InternalNormalItem
              internal_item_id="5"
              internal_item_parent_id="120"
              trans_unit_id="120-5"
              internal_item_type="Normal">
              <internal_items />
            </InternalNormalItem>
          </MarkdownSegment>
          <MarkdownSegment
            trans_unit_id="121">
            <SegmentId>3c0ea4ce-f1be-42f5-bcee-29c4403d4f70</SegmentId>
            <InternalNormalItem
              internal_item_id="1"
              internal_item_parent_id="121"
              trans_unit_id="121-1"
              internal_item_type="Normal">
              <internal_items />
            </InternalNormalItem>
          </MarkdownSegment>
          <MarkdownSegment
            trans_unit_id="122">
            <SegmentId>f11b8e3c-1792-484b-8362-85b218b707f6</SegmentId>
            <InternalNormalItem
              internal_item_id="1"
              internal_item_parent_id="122"
              trans_unit_id="122-1"
              internal_item_type="Normal">
              <internal_items />
            </InternalNormalItem>
          </MarkdownSegment>
        </paragraph_segments>
      </MarkdownBlockBase>
    </ArrayOfMarkdownBlockBase>
  </block_element>
  <references>
    <ArrayOfMarkdownLinkedReference xmlns:xsd="http://www.w3.org/2001/XMLSchema" xmlns:xsi="http://www.w3.org/2001/XMLSchema-instance" />
  </references>
</markdown_skeleton_root>